{
  "queryID": "ecafd427-5191-c66d-6fe2-a90196721582",
  "answer": {
    "1": {
      "startTime": [
        1517210532041
      ],
      "leaveTime": [
        1517210532111
      ],
      "isSelected": false
    },
    "2": {
      "startTime": [
        1517210506074
      ],
      "leaveTime": [
        1517210515473
      ],
      "isSelected": false
    },
    "3": {
      "startTime": [
        1517210394760,
        1517210533068,
        1517210552704
      ],
      "leaveTime": [
        1517210405144,
        1517210534123,
        1517210553006
      ],
      "isSelected": false
    },
    "4": {
      "startTime": [
        1517210341183
      ],
      "leaveTime": [
        1517210341413
      ],
      "isSelected": false
    },
    "5": {
      "startTime": [
        1517210380111
      ],
      "leaveTime": [
        1517210394726
      ],
      "isSelected": true
    },
    "6": {
      "startTime": [
        1517210355259,
        1517210523840,
        1517210552008
      ],
      "leaveTime": [
        1517210356328,
        1517210527206,
        1517210552074
      ],
      "isSelected": false
    },
    "7": {
      "startTime": [
        1517210530807,
        1517210548156
      ],
      "leaveTime": [
        1517210530829,
        1517210548289
      ],
      "isSelected": false
    },
    "8": {
      "startTime": [
        1517210354594,
        1517210527207,
        1517210551740
      ],
      "leaveTime": [
        1517210355236,
        1517210528009,
        1517210552008
      ],
      "isSelected": false
    },
    "9": {
      "startTime": [],
      "leaveTime": [],
      "isSelected": false
    },
    "10": {
      "startTime": [
        1517210301487,
        1517210320330,
        1517210334729,
        1517210354228,
        1517210529291,
        1517210551656
      ],
      "leaveTime": [
        1517210303647,
        1517210320447,
        1517210340896,
        1517210354264,
        1517210529374,
        1517210551692
      ],
      "isSelected": true
    },
    "11": {
      "startTime": [
        1517210357614,
        1517210434459,
        1517210532907,
        1517210534123,
        1517210552643
      ],
      "leaveTime": [
        1517210357747,
        1517210440543,
        1517210533039,
        1517210535274,
        1517210552703
      ],
      "isSelected": false
    },
    "12": {
      "startTime": [],
      "leaveTime": [],
      "isSelected": false
    },
    "13": {
      "startTime": [
        1517210414596
      ],
      "leaveTime": [
        1517210425276
      ],
      "isSelected": true
    },
    "14": {
      "startTime": [
        1517210356329,
        1517210522942,
        1517210552074
      ],
      "leaveTime": [
        1517210356412,
        1517210523558,
        1517210552223
      ],
      "isSelected": false
    },
    "15": {
      "startTime": [
        1517210469725
      ],
      "leaveTime": [
        1517210476009
      ],
      "isSelected": false
    },
    "16": {
      "startTime": [
        1517210356714,
        1517210505642,
        1517210515495,
        1517210531627,
        1517210536257,
        1517210552309
      ],
      "leaveTime": [
        1517210357433,
        1517210506028,
        1517210522440,
        1517210531976,
        1517210537224,
        1517210552350
      ],
      "isSelected": false
    },
    "17": {
      "startTime": [],
      "leaveTime": [],
      "isSelected": false
    },
    "18": {
      "startTime": [
        1517210408277,
        1517210412264
      ],
      "leaveTime": [
        1517210408360,
        1517210414596
      ],
      "isSelected": false
    },
    "19": {
      "startTime": [
        1517210356412,
        1517210522462,
        1517210531457,
        1517210537225,
        1517210552260
      ],
      "leaveTime": [
        1517210356713,
        1517210522941,
        1517210531607,
        1517210537773,
        1517210552309
      ],
      "isSelected": false
    },
    "20": {
      "startTime": [
        1517210405160,
        1517210406462,
        1517210408389
      ],
      "leaveTime": [
        1517210405160,
        1517210407398,
        1517210412244
      ],
      "isSelected": false
    },
    "21": {
      "startTime": [],
      "leaveTime": [],
      "isSelected": false
    },
    "22": {
      "startTime": [
        1517210343816
      ],
      "leaveTime": [
        1517210352979
      ],
      "isSelected": false
    },
    "23": {
      "startTime": [
        1517210341462,
        1517210354284,
        1517210529396,
        1517210549090
      ],
      "leaveTime": [
        1517210343762,
        1517210354428,
        1517210529860,
        1517210549641
      ],
      "isSelected": false
    },
    "24": {
      "startTime": [
        1517210340896
      ],
      "leaveTime": [
        1517210341163
      ],
      "isSelected": false
    },
    "25": {
      "startTime": [
        1517210530190,
        1517210548290
      ],
      "leaveTime": [
        1517210530806,
        1517210549089
      ],
      "isSelected": false
    },
    "26": {
      "startTime": [],
      "leaveTime": [],
      "isSelected": false
    },
    "27": {
      "startTime": [
        1517210537840
      ],
      "leaveTime": [
        1517210548155
      ],
      "isSelected": true
    },
    "28": {
      "startTime": [
        1517210498911
      ],
      "leaveTime": [
        1517210503807
      ],
      "isSelected": false
    },
    "29": {
      "startTime": [
        1517210441582
      ],
      "leaveTime": [
        1517210448426
      ],
      "isSelected": false
    },
    "30": {
      "startTime": [
        1517210303680,
        1517210310671,
        1517210314063,
        1517210319349,
        1517210320497,
        1517210354033,
        1517210528011
      ],
      "leaveTime": [
        1517210303880,
        1517210312331,
        1517210319066,
        1517210320197,
        1517210334695,
        1517210354195,
        1517210528776
      ],
      "isSelected": false
    },
    "31": {
      "startTime": [
        1517210476010
      ],
      "leaveTime": [
        1517210498890
      ],
      "isSelected": false
    },
    "32": {
      "startTime": [],
      "leaveTime": [],
      "isSelected": false
    },
    "33": {
      "startTime": [
        1517210529861
      ],
      "leaveTime": [
        1517210530157
      ],
      "isSelected": false
    },
    "34": {
      "startTime": [],
      "leaveTime": [],
      "isSelected": false
    },
    "35": {
      "startTime": [
        1517210303906,
        1517210312352,
        1517210352980
      ],
      "leaveTime": [
        1517210310647,
        1517210314029,
        1517210354011
      ],
      "isSelected": true
    },
    "36": {
      "startTime": [
        1517210503874,
        1517210532223,
        1517210535276,
        1517210552351
      ],
      "leaveTime": [
        1517210505406,
        1517210532377,
        1517210536257,
        1517210552593
      ],
      "isSelected": false
    },
    "37": {
      "startTime": [
        1517210458314
      ],
      "leaveTime": [
        1517210469691
      ],
      "isSelected": false
    },
    "38": {
      "startTime": [
        1517210358744
      ],
      "leaveTime": [
        1517210380110
      ],
      "isSelected": false
    },
    "39": {
      "startTime": [],
      "leaveTime": [],
      "isSelected": false
    },
    "40": {
      "startTime": [
        1517210425309
      ],
      "leaveTime": [
        1517210434426
      ],
      "isSelected": true
    },
    "41": {
      "startTime": [],
      "leaveTime": [],
      "isSelected": false
    },
    "42": {
      "startTime": [
        1517210343762,
        1517210354533
      ],
      "leaveTime": [
        1517210343813,
        1517210354569
      ],
      "isSelected": false
    },
    "43": {
      "startTime": [
        1517210357433,
        1517210440543,
        1517210448426,
        1517210532378,
        1517210552594
      ],
      "leaveTime": [
        1517210357613,
        1517210441560,
        1517210458291,
        1517210532907,
        1517210552642
      ],
      "isSelected": false
    },
    "44": {
      "startTime": [],
      "leaveTime": [],
      "isSelected": false
    },
    "45": {
      "startTime": [],
      "leaveTime": [],
      "isSelected": false
    }
  },
  "enterInstructionPageTime": 1517210207146,
  "enterTaskTime": 1517210301420,
  "submittedTime": 1517210556747
}
